README.md
setup.cfg
setup.py
lib/__init__.py
lib/activeboards.py
lib/autobool.py
lib/board.py
lib/config.py
lib/connection.py
lib/esptool.py
lib/fileops.py
lib/flasher.py
lib/getch.py
lib/main.py
lib/mdns_client.py
lib/printing.py
lib/shell.py
lib/timeit.py
lib/util.py
lib/version.py
lib/do/__init__.py
lib/do/_do_osdebug.py
lib/do/do_boards.py
lib/do/do_cat.py
lib/do/do_cd.py
lib/do/do_config.py
lib/do/do_connect.py
lib/do/do_cp.py
lib/do/do_debug.py
lib/do/do_disconnect.py
lib/do/do_edit.py
lib/do/do_flash.py
lib/do/do_help.py
lib/do/do_ip.py
lib/do/do_ls.py
lib/do/do_mac.py
lib/do/do_mdns.py
lib/do/do_mkdir.py
lib/do/do_ports.py
lib/do/do_quiet.py
lib/do/do_repl.py
lib/do/do_rm.py
lib/do/do_rsync.py
lib/do/do_run.py
lib/do/do_shell.py
lib/do/do_version.py
lib/do/__init__.py
lib/do/_do_osdebug.py
lib/do/do_boards.py
lib/do/do_cat.py
lib/do/do_cd.py
lib/do/do_config.py
lib/do/do_connect.py
lib/do/do_cp.py
lib/do/do_debug.py
lib/do/do_disconnect.py
lib/do/do_edit.py
lib/do/do_flash.py
lib/do/do_help.py
lib/do/do_ip.py
lib/do/do_ls.py
lib/do/do_mac.py
lib/do/do_mdns.py
lib/do/do_mkdir.py
lib/do/do_ports.py
lib/do/do_quiet.py
lib/do/do_repl.py
lib/do/do_rm.py
lib/do/do_rsync.py
lib/do/do_run.py
lib/do/do_shell.py
lib/do/do_version.py
shell49.egg-info/PKG-INFO
shell49.egg-info/SOURCES.txt
shell49.egg-info/dependency_links.txt
shell49.egg-info/entry_points.txt
shell49.egg-info/requires.txt
shell49.egg-info/top_level.txt