Metadata-Version: 1.1
Name: shell49
Version: 0.1.10
Summary: Micropython remote shell
Home-page: https://github.com/bboser/shell49
Author: Bernhard Boser
Author-email: boser@berkeley.edu
License: MIT
Keywords: micropython,shell,shell49
Platform: UNKNOWN
Classifier: Development Status :: 3 - Alpha
Classifier: Environment :: Console
Classifier: Intended Audience :: Developers
Classifier: License :: OSI Approved :: MIT License
Classifier: Natural Language :: English
Classifier: Operating System :: POSIX :: Linux
Classifier: Programming Language :: Python
Classifier: Programming Language :: Python :: 3.6
Classifier: Topic :: Software Development :: Embedded Systems
Classifier: Topic :: System :: Shells
Classifier: Topic :: Terminals :: Serial
Classifier: Topic :: Terminals :: Telnet
Classifier: Topic :: Utilities
